llm_generation_server/component_base.py
llm_generation_server/server.py
llm_generation_server/dist/favicon.ico
llm_generation_server/dist/index.html
llm_generation_server/dist/assets/index-5a602ef5.js
llm_generation_server/dist/assets/index-71e137a6.css
llm_generation_server/elements/barchart_element.py
llm_generation_server/elements/element_base.py
llm_generation_server/elements/plain_text_element.py
llm_generation_server/elements/selector_elements.py
llm_generation_server/elements/table_element.py
llm_generation_server/elements/utils.py
llm_generation_server-0.0.21.dist-info/LICENSE
llm_generation_server-0.0.21.dist-info/METADATA
llm_generation_server-0.0.21.dist-info/WHEEL
llm_generation_server-0.0.21.dist-info/top_level.txt
llm_generation_server-0.0.21.dist-info/RECORD
