Metadata-Version: 2.1
Name: llm-generation-server
Version: 0.0.21
Summary: Simple full stack app for displaying distribution of next token.
Author-email: "Frantisek Trebuna (gortibaldik)" <ferotre@gmail.com>
Project-URL: Homepage, https://github.com/gortibaldik/visualize_llm_generation
Project-URL: Bug Tracker, https://github.com/gortibaldik/visualize_llm_generation/issues
Classifier: Programming Language :: Python :: 3
Classifier: License :: OSI Approved :: MIT License
Classifier: Operating System :: OS Independent
Requires-Python: >=3.9
License-File: LICENSE
Requires-Dist: Flask (>=2.3.1)
Requires-Dist: Flask-Cors (>=3.0.10)
